CHANGES.txt
LICENSE.txt
MANIFEST.in
README.txt
distribute_setup.py
setup.py
aidan/__init__.py
aidan.egg-info/PKG-INFO
aidan.egg-info/SOURCES.txt
aidan.egg-info/dependency_links.txt
aidan.egg-info/top_level.txt