Metadata-Version: 1.0
Name: aidan
Version: 0.1.2
Summary: UNKNOWN
Home-page: UNKNOWN
Author: UNKNOWN
Author-email: UNKNOWN
License: See LICENSE.txt
Platform: UNKNOWN
